letshelp_letsencrypt/__init__.py
letshelp_letsencrypt-0.6.0.dist-info/DESCRIPTION.rst
letshelp_letsencrypt-0.6.0.dist-info/METADATA
letshelp_letsencrypt-0.6.0.dist-info/RECORD
letshelp_letsencrypt-0.6.0.dist-info/WHEEL
letshelp_letsencrypt-0.6.0.dist-info/entry_points.txt
letshelp_letsencrypt-0.6.0.dist-info/metadata.json
letshelp_letsencrypt-0.6.0.dist-info/top_level.txt
